behaviortree/README.md
behaviortree/__init__.py
behaviortree/tree.py
behaviortree/version
behaviortree-0.0.4.dist-info/LICENSE
behaviortree-0.0.4.dist-info/METADATA
behaviortree-0.0.4.dist-info/WHEEL
behaviortree-0.0.4.dist-info/top_level.txt
behaviortree-0.0.4.dist-info/RECORD
